README.md
setup.py
asptl/__init__.py
asptl/file.py
asptl/lists.py
asptl/thread.py
asptl/windows.py
asptl.egg-info/PKG-INFO
asptl.egg-info/SOURCES.txt
asptl.egg-info/dependency_links.txt
asptl.egg-info/top_level.txt