Metadata-Version: 2.1
Name: asptl
Version: 1.0.0
Summary: 
